data_validator/__init__.py
data_validator/errors.py
data_validator/fields.py
data_validator/serializer.py
data_validator/validator.py
famo_data_validator-0.1.6.dist-info/licenses/LICENSE
famo_data_validator-0.1.6.dist-info/METADATA
famo_data_validator-0.1.6.dist-info/WHEEL
famo_data_validator-0.1.6.dist-info/top_level.txt
famo_data_validator-0.1.6.dist-info/RECORD
