Metadata-Version: 2.4
Name: famo-data-validator
Version: 0.1.6
Summary: Python data validation library with type hints and schema support
Home-page: https://github.com/famo-codes/data_validator
Author: Famo
Author-email: CoreByMostafa@gmail.com
Keywords: data validation serializer schema python
Classifier: Development Status :: 4 - Beta
Classifier: Programming Language :: Python :: 3
Classifier: Programming Language :: Python :: 3.9
Classifier: License :: OSI Approved :: MIT License
Classifier: Operating System :: OS Independent
Classifier: Intended Audience :: Developers
Classifier: Topic :: Software Development :: Libraries
Requires-Python: >=3.10
License-File: LICENSE
Requires-Dist: validators>=0.35.0
Dynamic: author
Dynamic: author-email
Dynamic: classifier
Dynamic: description
Dynamic: description-content-type
Dynamic: home-page
Dynamic: keywords
Dynamic: license-file
Dynamic: requires-dist
Dynamic: requires-python
Dynamic: summary
